sqlstatement/__init__.py
sqlstatement/sql.py
sqlstatement/sqlactions.py
sqlstatement/sqlentities.py
sqlstatement/sqlparseutils.py
sqlstatement-0.0.1.dist-info/METADATA
sqlstatement-0.0.1.dist-info/WHEEL
sqlstatement-0.0.1.dist-info/licenses/LICENSE
sqlstatement-0.0.1.dist-info/RECORD
