Metadata-Version: 2.1
Name: sqlstatement
Version: 0.0.1
Summary: Python library for parsing the sql statements into easy to use metadata about sql operation, columns, filtering conditions and more. Visit the project at https://github.com/lako55/py-sqlstatement for more details.
Project-URL: Homepage, https://github.com/lako55/py-sqlstatement
Project-URL: Bug Tracker, https://github.com/lako55/py-sqlstatement
Author-email: lako55 <zosa.project@gmail.com>
License: BSD 3-Clause License
Keywords: parser,parsing,parsing-library,sql
Classifier: License :: OSI Approved :: BSD License
Classifier: Operating System :: OS Independent
Classifier: Programming Language :: Python :: 3
Classifier: Programming Language :: SQL
Classifier: Topic :: Software Development :: Libraries
Requires-Python: >=3.10
Requires-Dist: sqlparse>=0.4.2
